{"_id":"64753fcf2c12805eb34cc382","userId":"422347593625108490","badges":[{"name":"tonk","badge":"https://gb.obamabot.me/83c80766a17a79b1bfd155e34b269f11c19604ec.png","_id":"64753fcf2c12805eb34cc383","pending":false},{"name":"walcc","badge":"https://gb.obamabot.me/c12c808ebcef736560008b90312529887f409e72.gif","_id":"647542eb2c12805eb34cc38d","pending":false},{"name":"epinephrine","badge":"https://gb.obamabot.me/b07b895b2a19e027adfd3f0d5d37a63a4e616894.gif","_id":"64a1f7017057f73db5e6fb95","pending":false}],"__v":2,"blocked":false}