{"_id":"643a28a68025f764d7e39fae","userId":"938557606820204625","badge":"https://cdn.discordapp.com/emojis/985678066154106910.webp?size=48","name":"This guy is Cringe","__v":14,"badges":[{"name":"This guy is Cringe","badge":"https://cdn.discordapp.com/emojis/985678066154106910.webp?size=48","_id":"644dda063d10719eda8ec26d"},{"name":"Wattson","badge":"https://media.discordapp.net/attachments/751155896024826018/1125179178896076870/Badge_Imperial_Wattson.png","_id":"64a1f3227057f73db5e6fb81"},{"name":"CSS 3 Nerd 🤓","badge":"https://media.discordapp.net/attachments/751155896024826018/1125632830689529867/Badge_CSS_3_Apex_Style.png","_id":"64a395997057f73db5e6fc18"},{"name":"Royal Crown 👑","badge":"https://media.discordapp.net/attachments/751155896024826018/1125632830941171783/Badge_Dev_Crown_Apex_Style.png","_id":"64a395d57057f73db5e6fc3a"}]}